pretix_dob_validation/__init__.py
pretix_dob_validation/apps.py
pretix_dob_validation/signals.py
pretix_dob_validation/urls.py
pretix_dob_validation/views.py
pretix_dob_validation/locale/de/LC_MESSAGES/django.mo
pretix_dob_validation/locale/de/LC_MESSAGES/django.po
pretix_dob_validation/locale/de_Informal/.gitkeep
pretix_dob_validation/locale/de_Informal/LC_MESSAGES/django.mo
pretix_dob_validation/locale/de_Informal/LC_MESSAGES/django.po
pretix_dob_validation/static/pretix_dob_validation/.gitkeep
pretix_dob_validation/templates/pretix_dob_validation/.gitkeep
pretix_dob_validation/templates/pretix_dob_validation/settings.html
pretix_dob_validation-1.1.0.dist-info/LICENSE
pretix_dob_validation-1.1.0.dist-info/METADATA
pretix_dob_validation-1.1.0.dist-info/WHEEL
pretix_dob_validation-1.1.0.dist-info/entry_points.txt
pretix_dob_validation-1.1.0.dist-info/top_level.txt
pretix_dob_validation-1.1.0.dist-info/RECORD
