Metadata-Version: 2.1
Name: pretix-dob-validation
Version: 1.1.0
Summary: DOB Validation
Home-page: https://github.com/pretix-unofficial/pretix-dob-validation
Author: pretix
Author-email: support@pretix.eu
License: Apache
License-File: LICENSE
